{"PkgId":"AngleSharp","VersionInfos":[{"Version":"0.2.0","Tfs":[]},{"Version":"0.2.1","Tfs":[]},{"Version":"0.2.2","Tfs":[]},{"Version":"0.2.3","Tfs":[]},{"Version":"0.2.4","Tfs":[]},{"Version":"0.2.5","Tfs":[]},{"Version":"0.2.6","Tfs":[]},{"Version":"0.2.7","Tfs":[]},{"Version":"0.2.8","Tfs":[]},{"Version":"0.2.9","Tfs":[]},{"Version":"0.3.0","Tfs":[]},{"Version":"0.3.1","Tfs":[]},{"Version":"0.3.2","Tfs":[]},{"Version":"0.3.3","Tfs":[]},{"Version":"0.3.4","Tfs":[]},{"Version":"0.3.5","Tfs":[]},{"Version":"0.3.6","Tfs":[]},{"Version":"0.3.7","Tfs":[]},{"Version":"0.4.0","Tfs":[]},{"Version":"0.5.0","Tfs":[]},{"Version":"0.5.1","Tfs":[]},{"Version":"0.6.0","Tfs":[]},{"Version":"0.6.1","Tfs":[]},{"Version":"0.7.0","Tfs":[]},{"Version":"0.8.0","Tfs":[]},{"Version":"0.8.1","Tfs":[]},{"Version":"0.8.2","Tfs":[".NETFramework4.0","Silverlight5.0"]},{"Version":"0.8.3","Tfs":[".NETFramework4.0","Silverlight5.0"]},{"Version":"0.8.4","Tfs":[".NETPortable0.0-windows8\u002Bnet45\u002Bwindowsphone8\u002Bwpa",".NETFramework4.5",".NETFramework4.0","Silverlight5.0"]},{"Version":"0.8.4.1","Tfs":[".NETPortable0.0-windows8\u002Bnet45\u002Bwindowsphone8\u002Bwpa",".NETFramework4.5",".NETFramework4.0","Silverlight5.0"]},{"Version":"0.8.5","Tfs":[".NETPortable0.0-windows8\u002Bnet45\u002Bwindowsphone8\u002Bwpa",".NETFramework4.5",".NETFramework4.0","Silverlight5.0"]},{"Version":"0.8.6","Tfs":[".NETPortable0.0-windows8\u002Bnet45\u002Bwindowsphone8\u002Bwpa",".NETFramework4.5",".NETFramework4.0","Silverlight5.0"]},{"Version":"0.8.7","Tfs":[".NETPortable0.0-windows8\u002Bnet45\u002Bwindowsphone8\u002Bwpa",".NETFramework4.5",".NETFramework4.0","Silverlight5.0"]},{"Version":"0.8.7.1","Tfs":[".NETPortable0.0-windows8\u002Bnet45\u002Bwindowsphone8\u002Bwpa",".NETFramework4.5",".NETFramework4.0","Silverlight5.0"]},{"Version":"0.8.8","Tfs":[".NETPortable0.0-windows8\u002Bnet45\u002Bwindowsphone8\u002Bwpa",".NETFramework4.5",".NETFramework4.0","Silverlight5.0"]},{"Version":"0.8.9","Tfs":[".NETPortable0.0-windows8\u002Bnet45\u002Bwindowsphone8\u002Bwpa",".NETFramework4.5",".NETFramework4.0","Silverlight5.0"]},{"Version":"0.9.0","Tfs":[".NETPortable0.0-windows8\u002Bnet45\u002Bwindowsphone8\u002Bwpa",".NETFramework4.5",".NETFramework4.0","Silverlight5.0"]},{"Version":"0.9.1","Tfs":[".NETPortable0.0-windows8\u002Bnet45\u002Bwindowsphone8\u002Bwpa",".NETFramework4.5",".NETFramework4.0","Silverlight5.0"]},{"Version":"0.9.2","Tfs":[".NETPortable0.0-windows8\u002Bnet45\u002Bwindowsphone8\u002Bwpa",".NETFramework4.5",".NETFramework4.0","Silverlight5.0"]},{"Version":"0.9.3","Tfs":[".NETPortable0.0-windows8\u002Bnet45\u002Bwindowsphone8\u002Bwpa",".NETFramework4.5",".NETFramework4.0","Silverlight5.0"]},{"Version":"0.9.4","Tfs":[".NETPortable0.0-windows8\u002Bnet45\u002Bwindowsphone8\u002Bwpa",".NETFramework4.5",".NETFramework4.0","Silverlight5.0"]},{"Version":"0.9.5","Tfs":[".NETPlatform5.0",".NETPortable0.0-windows8\u002Bnet45\u002Bwindowsphone8\u002Bwpa",".NETFramework4.5",".NETFramework4.0","Silverlight5.0"]},{"Version":"0.9.6","Tfs":[".NETPlatform5.0",".NETPortable0.0-Profile259",".NETFramework4.5",".NETFramework4.0","Silverlight5.0"]},{"Version":"0.9.7","Tfs":[".NETStandard1.0",".NETPortable0.0-Profile259",".NETFramework4.5",".NETFramework4.0","Silverlight5.0"]},{"Version":"0.9.8","Tfs":[".NETStandard1.0",".NETPortable0.0-Profile259",".NETFramework4.5",".NETFramework4.0","Silverlight5.0"]},{"Version":"0.9.8.1","Tfs":[".NETStandard1.0",".NETPortable0.0-Profile259",".NETFramework4.5",".NETFramework4.0","Silverlight5.0"]},{"Version":"0.9.9","Tfs":[".NETStandard1.0",".NETPortable0.0-Profile259",".NETFramework4.5",".NETFramework4.0","Silverlight5.0"]},{"Version":"0.9.9.1","Tfs":[".NETStandard1.0",".NETPortable0.0-Profile259",".NETFramework4.5",".NETFramework4.0","Silverlight5.0"]},{"Version":"0.9.9.2","Tfs":[".NETStandard1.0",".NETPortable0.0-Profile259",".NETFramework4.5",".NETFramework4.0","Silverlight5.0"]},{"Version":"0.9.10","Tfs":[".NETStandard1.0",".NETPortable0.0-Profile259",".NETFramework4.5",".NETFramework4.0","Silverlight5.0"]},{"Version":"0.9.11","Tfs":[".NETStandard1.0",".NETPortable0.0-Profile259",".NETFramework4.5",".NETFramework4.0","Silverlight5.0"]},{"Version":"0.10.0","Tfs":[]},{"Version":"0.10.1","Tfs":[".NETStandard1.3",".NETStandard2.0",".NETFramework4.6"]},{"Version":"0.11.0","Tfs":[".NETStandard1.3",".NETStandard2.0",".NETFramework4.6"]},{"Version":"0.12.0","Tfs":[".NETStandard1.3",".NETStandard2.0",".NETFramework4.6"]},{"Version":"0.12.1","Tfs":[".NETStandard1.3",".NETStandard2.0",".NETFramework4.6"]},{"Version":"0.13.0","Tfs":[".NETStandard1.3",".NETStandard2.0",".NETFramework4.6"]},{"Version":"0.14.0","Tfs":[".NETStandard1.3",".NETStandard2.0",".NETFramework4.6",".NETFramework4.6.1",".NETFramework4.7.2"]},{"Version":"0.15.0","Tfs":[".NETStandard2.0",".NETFramework4.6",".NETFramework4.6.1",".NETFramework4.7.2"]},{"Version":"0.16.0","Tfs":[".NETStandard2.0",".NETFramework4.6",".NETFramework4.6.1",".NETFramework4.7.2"]},{"Version":"0.16.1","Tfs":[".NETStandard2.0",".NETFramework4.6",".NETFramework4.6.1",".NETFramework4.7.2"]},{"Version":"0.17.0","Tfs":[".NETStandard2.0",".NETFramework4.6.1",".NETFramework4.7.2"]},{"Version":"0.17.1","Tfs":[".NETStandard2.0",".NETFramework4.6.1",".NETFramework4.7.2"]},{"Version":"1.0.0","Tfs":[".NETStandard2.0",".NETFramework4.6.1",".NETFramework4.7.2","net6.0","net7.0"]},{"Version":"1.0.1","Tfs":[".NETStandard2.0",".NETFramework4.6.1",".NETFramework4.7.2","net6.0","net7.0"]}]}